nested_django_serializer/__init__.py
nested_django_serializer/django/__init__.py
nested_django_serializer/django/serializers/__init__.py
nested_django_serializer/django/serializers/base.py
nested_django_serializer/django/serializers/json.py
nested_django_serializer/django/serializers/python.py
nested_django_serializer-1.1.0.dist-info/AUTHORS
nested_django_serializer-1.1.0.dist-info/LICENSE
nested_django_serializer-1.1.0.dist-info/METADATA
nested_django_serializer-1.1.0.dist-info/WHEEL
nested_django_serializer-1.1.0.dist-info/top_level.txt
nested_django_serializer-1.1.0.dist-info/RECORD
