Metadata-Version: 2.1
Name: nested-django-serializer
Version: 1.1.0
Summary: Modifies the Django serializer such that it fully serializes foreign key relations.
Author: Colton Schneider
License: MIT
Project-URL: Github, https://github.com/colton305/nested-django-serializer
Keywords: django json serializer
Classifier: Programming Language :: Python :: 3
Classifier: Operating System :: OS Independent
Classifier: Environment :: Web Environment
Classifier: Intended Audience :: Developers
Classifier: License :: OSI Approved :: MIT License
Classifier: Topic :: Utilities
Classifier: Framework :: Django
Requires-Python: >=3.8
License-File: LICENSE
License-File: AUTHORS
Requires-Dist: django
